.hgignore
.hgtags
CHANGES.txt
LICENSE.txt
MANIFEST.in
README.txt
bootstrap.py
bootstrap.pyo
buildout.cfg
setup.py
js/__init__.py
js.jquery_form.egg-info/PKG-INFO
js.jquery_form.egg-info/SOURCES.txt
js.jquery_form.egg-info/dependency_links.txt
js.jquery_form.egg-info/entry_points.txt
js.jquery_form.egg-info/namespace_packages.txt
js.jquery_form.egg-info/not-zip-safe
js.jquery_form.egg-info/requires.txt
js.jquery_form.egg-info/top_level.txt
js/jquery_form/__init__.py
js/jquery_form/test_jquery_form.txt
js/jquery_form/resources/README.txt
js/jquery_form/resources/jquery.form.js
js/jquery_form/resources/jquery.form.min.js