Metadata-Version: 1.0
Name: js.jquery-form
Version: 3.09
Summary: Fanstatic packaging of jQuery Form
Home-page: UNKNOWN
Author: Fanstatic Developers
Author-email: fanstatic@googlegroups.com
License: BSD
Platform: UNKNOWN
